[
    {
        "question": "Which among the following is NOT an exception?",
        "options": [
            "a) Stack Overflow",
            "b) Arithmetic Overflow or underflow",
            "c) Incorrect Arithmetic Expression",
            "d) All of the mentioned"
        ],
        "answer": "c",
        "explanation": "None."
    },
    {
        "question": "Which among the following is considered as .NET Exception class?",
        "options": [
            "a) Exception",
            "b) StackUnderflow Exception",
            "c) File bound Exception",
            "d) All of the mentioned"
        ],
        "answer": "b",
        "explanation": "None."
    },
    {
        "question": "Which of the following is the object oriented way to handle run time errors?",
        "options": [
            "a) Error codes",
            "b) HERRESULT",
            "c) OnError",
            "d) Exceptions"
        ],
        "answer": "d",
        "explanation": "None."
    },
    {
        "question": "Select the statements which describe the correct usage of exception handling over conventional error handling approaches?",
        "options": [
            "a) As errors can be ignored but exceptions cannot be ignored",
            "b) Exception handling allows separation of program\u2019s logic  from error handling logic making software more reliable and maintainable",
            "c) try \u2013 catch \u2013 finally structure allows guaranteed cleanup in event of errors under all circumstances",
            "d) All of the mentioned"
        ],
        "answer": "d",
        "explanation": "None."
    },
    {
        "question": "Select the correct statement about an Exception?",
        "options": [
            "a) It occurs during loading of program",
            "b) It occurs during Just-In-Time compilation",
            "c) It occurs at run time",
            "d) All of the mentioned"
        ],
        "answer": "c",
        "explanation": "Explanation:None."
    },
    {
        "question": "Which of these keywords must be used to monitor exceptions?",
        "options": [
            "a) try",
            "b) finally",
            "c) throw",
            "d) catch"
        ],
        "answer": "a",
        "explanation": "None."
    },
    {
        "question": "Which of these keywords is used to manually throw an exception?",
        "options": [
            "a) try",
            "b) finally",
            "c) throw",
            "d) catch"
        ],
        "answer": "c",
        "explanation": "None."
    },
    {
        "question": "What will be the output of the following C# code?",
        "options": [],
        "answer": "b",
        "explanation": "Explanation:None."
    },
    {
        "question": "What will be the output of the following C# code?",
        "options": [],
        "answer": "b",
        "explanation": "1 / 0,  hence system out of flow exception error."
    },
    {
        "question": "Which of the following is the wrong statement about exception handling in C#.NET?",
        "options": [
            "a) finally clause is used to perform cleanup operations of closing network and database connections",
            "b) a program can contain multiple finally clauses",
            "c) the statement in final clause will get executed no matter whether an exception occurs or not",
            "d) all of the mentioned"
        ],
        "answer": "b",
        "explanation": "None."
    },
    {
        "question": "What will be the output of the following C# code?",
        "options": [],
        "answer": "b",
        "explanation": "Run time Error of division by zero."
    }
]