[
    {
        "question": "1) How many numbers of the element in the open IoT architecture?",
        "options": [
            "Four elements",
            "Five elements",
            "Six elements",
            "Seven elements"
        ],
        "answer": "Seven elements",
        "explanation": "Description: There are seven numbers of elements in the open IoT architecture:",
        "codeblock": null
    },
    {
        "question": "2) Which of the following is the way in which an IoT device is associated with data?",
        "options": [
            "Internet",
            "Cloud",
            "Automata",
            "Network"
        ],
        "answer": "Cloud",
        "explanation": "Description: Cloud-based services provide a way for IoT devices to be connected to data. For example: Just as the WWW (World Wide Web) runs on the Internet, so does IoT.",
        "codeblock": null
    },
    {
        "question": "3) Which of the following IoT networks has a very short range?",
        "options": [
            "Short Network",
            "LPWAN",
            "SigFox",
            "Short-range Wireless Network"
        ],
        "answer": "Short Range Wireless Network",
        "explanation": "Description: Short-range wireless networks have a very short range. This type of network is used for applications running in the local environment. The best example of this network is Wi-Fi and Bluetooth.",
        "codeblock": null
    },
    {
        "question": "4) What is the full form of the LPWAN?",
        "options": [
            "Low Protocol Wide Area Network",
            "Low Power Wide Area Network",
            "Long Protocol Wide Area Network",
            "Long Power Wide Area Network"
        ],
        "answer": "Low Power Wide Area Network",
        "explanation": "Description: The full form of the LPWAN is Low Power Wide Area Network. LPWAN is a type of wireless telecommunication, and it is specially designed for M2M (Machine to Machine) and IoT devices.",
        "codeblock": null
    },
    {
        "question": "5) An IoT network is a collection of ______ devices.",
        "options": [
            "Signal",
            "Machine to Machine",
            "Interconnected",
            "Network to Network"
        ],
        "answer": "Interconnected",
        "explanation": "Description: An IoT network is a collection of interconnected devices that communicate with other devices without human involvement.",
        "codeblock": null
    },
    {
        "question": "6) Which one of the following is not an IoT device?",
        "options": [
            "Amazon echo voice controller",
            "Google Home",
            "Nest Smoke Alarm",
            "None of these"
        ],
        "answer": "None of the these",
        "explanation": "Description: These are all IoT devices. Google Home is a smart speaker that obeys all the commands given by the user. The Amazon Echo Voice Controller is also a smart speaker. The Nest Smoke Alarm is an IoT device that sends a smoke alert message to the user when a fire occurs.",
        "codeblock": null
    },
    {
        "question": "7) What is the main purpose of WoT (Web of Things) in the IoT?",
        "options": [
            "Improve the usability and interoperability",
            "Reduce the security",
            "Complex the development",
            "Increase the cost"
        ],
        "answer": "Improve the usability and interoperability",
        "explanation": "Description: The main purpose of the Web of Things is to improve the usability and interoperability in IoT. Developing IoT Apps through WoT is much easier, faster, and less expensive.",
        "codeblock": null
    },
    {
        "question": "8) What is the Arduino UNO?",
        "options": [
            "Software",
            "Hardware device",
            "Network",
            "Protocol"
        ],
        "answer": "Hardware device",
        "explanation": "Description: The Arduino Uno is a hardware device that is based on the Microchip ATmega328P microcontroller. It has been developed by Arduino.cc.",
        "codeblock": null
    },
    {
        "question": "9) ______ allows the user to control electronic components.",
        "options": [
            "Android API",
            "RETful API",
            "MQTT API",
            "CoAP API"
        ],
        "answer": "RETful API",
        "explanation": "Description: The RETful API allows the user to control the electronic components connected to the Intel Galileo Gen 2 board via HTTP requests.",
        "codeblock": null
    },
    {
        "question": "10) Which of the following is not an application of IoT?",
        "options": [
            "Wearables",
            "Smart Grid",
            "Arduino",
            "Smart City"
        ],
        "answer": "Arduino",
        "explanation": "Description: The Arduino Uno is a hardware device that is based on the Microchip ATmega328P microcontroller.",
        "codeblock": null
    },
    {
        "question": "11) Which one of the following protocols is lightweight?",
        "options": [
            "IP",
            "HTTP",
            "MQTT",
            "CoAP"
        ],
        "answer": "MQTT",
        "explanation": "Description: The full form of the MQTT is Message Queue Telemetry Transport. It is a lightweight messaging protocol that runs over the TCP / IP protocol.",
        "codeblock": null
    },
    {
        "question": "12) What is the role of Big Data in IoT's Smart Grid architecture?",
        "options": [
            "Filter the data",
            "Locked the data",
            "Store data",
            "None of the these"
        ],
        "answer": "Store data",
        "explanation": "Description: The main role of Big Data is to store data on a real-time basis. It uses multiple storage technologies to store the data.",
        "codeblock": null
    },
    {
        "question": "13) What is the real example of a smart grid device in IoT?",
        "options": [
            "Mobile phone",
            "Television",
            "Smart Speaker",
            "Smart Meters"
        ],
        "answer": "Smart Meters",
        "explanation": "Description: Smart Grid is used to monitor the power supply. Consumers' data is collected using a smart grid, and that data is analyzed and distributed to the consumers. The real example of a smart grid device is a smart meter.",
        "codeblock": null
    },
    {
        "question": "14) What is the full form of the MQTT?",
        "options": [
            "Multi-Queue Telemetry Things",
            "Multiple Queue Telemetry Things",
            "Message Queue Telemetry Things",
            "Message Queue Telemetry Transport"
        ],
        "answer": "Message Queue Telemetry Transport",
        "explanation": "Description: The full form of the MQTT is Message Queue Telemetry Transport. It is a lightweight messaging protocol that runs over the TCP / IP protocol.",
        "codeblock": null
    },
    {
        "question": "15) What is the full form of ICT?",
        "options": [
            "InterConnect Technology",
            "Internet Connection Topology",
            "Information and Communication Technology",
            "Infer Communication Topology"
        ],
        "answer": "Information and Communication Technology",
        "explanation": "Description: The full form of ICT is Information and Communication Technology. ICT is a multidimensional term for the IT sector that refers to all communication technologies, including the Internet, wireless networks, cell phones, computers, and software.",
        "codeblock": null
    },
    {
        "question": "16) Which of the following frequencies is correct for the Galileo gen 2 board?",
        "options": [
            "250 MHz",
            "400 MHz",
            "450 MHz",
            "300 MHz"
        ],
        "answer": "400 MHz",
        "explanation": "Description: The frequency of this board is 400 MHz. The Galileo gen 2 board frequency gives the speed of operation of the board. Therefore, the speed increases as the frequency increases.",
        "codeblock": null
    },
    {
        "question": "17) What is the full form of IANA?",
        "options": [
            "Inter-Assessment-Number-Access",
            "Internet-Association-Numbers-Authority",
            "International-Aid-for-Network-Authority",
            "Internet-Assigned-Numbers-Authority"
        ],
        "answer": "Internet-Assigned-Numbers-Authority",
        "explanation": "Description: The full form of IANA is Internet-Assigned-Numbers-Authority. It is an administrative function of the Internet that monitors the IP addresses and domain names.",
        "codeblock": null
    },
    {
        "question": "18) What is the standard port number of secure MQTT?",
        "options": [
            "1883",
            "8000",
            "8883",
            "8888"
        ],
        "answer": "8883",
        "explanation": "Description: The standard port number of Secure MQTT is 8883, and it is registered in IANA for Secure MQTT.",
        "codeblock": null
    },
    {
        "question": "19) Which of the following layers provides end-to-end communication in IoT?",
        "options": [
            "Logical layer",
            "Data link layer",
            "Transport layer",
            "Session layer"
        ],
        "answer": "Transport layer",
        "explanation": "Description: The transport layer focuses on end-to-end communication, and it gives reliability and congestion avoidance that packets will be delivered in the same way as the user sent the packet.",
        "codeblock": null
    },
    {
        "question": "20) Which of the following devices is used to measure the gases or liquid?",
        "options": [
            "Optical Sensor",
            "Gas Sensor",
            "Smoke Sensor",
            "Pressure sensor"
        ],
        "answer": "Pressure sensor",
        "explanation": "Description: The pressure sensor is used to measure the gases or liquid. Pressure is the expression of a force that is necessary to prevent fluid from expansion.",
        "codeblock": null
    },
    {
        "question": "21) Which interface does the fingerprint sensor use?",
        "options": [
            "UART interface",
            "CoAP interface",
            "SPI interface",
            "I2P interface"
        ],
        "answer": "UART interface",
        "explanation": "Description: The fingerprint sensor uses a UART interface to store fingerprint data. It can be configured in 1:1 or 1:N mode to identify the person.",
        "codeblock": null
    },
    {
        "question": "22) Which of the following protocols is used by USART?",
        "options": [
            "RS32",
            "RS232C",
            "4RS85",
            "All of the these"
        ],
        "answer": "RS232C",
        "explanation": "Description: The most commonly used protocol for USART in asynchronous mode is RS232C. This protocol describes the physical interface for relatively low-speed serial data-communication between devices and computers.",
        "codeblock": null
    },
    {
        "question": "23) What is the full form of HDLC?",
        "options": [
            "Higher Data Level Communication",
            "Higher Data Link Communication",
            "High-level Data Link Control",
            "High Data Level Control"
        ],
        "answer": "High-level Data Link Control",
        "explanation": "Description: The full form of the HDLC is High level Data Link Control. It is a communication protocol. It is used to transmit data between nodes and data points.",
        "codeblock": null
    },
    {
        "question": "24) Which of the following \"bit\" defines the address bit in the control register?",
        "options": [
            "ML",
            "MM",
            "RXWake",
            "None of the these"
        ],
        "answer": "MM",
        "explanation": "Description: The MM bit defines the address bit in the control register.",
        "codeblock": null
    },
    {
        "question": "25) What is another name for I2C?",
        "options": [
            "Signal wire interface",
            "Two wire interfaces",
            "UART",
            "USART"
        ],
        "answer": "Two wire interface",
        "explanation": "Description: The I2C protocol is also known as the two-wire interface. It is a simple serial-communication-protocol that uses pins of a microcontroller, named as serial clock (SCL) and serial data (SDA).",
        "codeblock": null
    },
    {
        "question": "26) When the clock line SCL is high, the SDA is ____ transitioned.",
        "options": [
            "Low",
            "High",
            "Medium",
            "All of the these"
        ],
        "answer": "Low",
        "explanation": "Description: When the clock line SCL is high, the SDA is low transitioned. Under normal circumstances, this does not happen, as you can see in the subsequent clock pulses that the data line is stable in one state, either high or low, when the clock line is high.",
        "codeblock": null
    },
    {
        "question": "27) Which of the following protocols does the secure digital card application use?",
        "options": [
            "XMPP",
            "SPI",
            "MQTT",
            "HTTPS"
        ],
        "answer": "SPI",
        "explanation": "Description: SPI stands for Serial Peripheral Interface. The SPI protocol is commonly used to secure digital card applications and liquid crystal displays.",
        "codeblock": null
    },
    {
        "question": "28) How many logic signals are there in the SPI protocol?",
        "options": [
            "Five signals",
            "Six signals",
            "Nine signals",
            "Zero signals"
        ],
        "answer": "Five signals",
        "explanation": "Description: There are five logic signals in the SPI protocol.",
        "codeblock": null
    },
    {
        "question": "29) What does MOSI mean?",
        "options": [
            "MOSI is a network line.",
            "MOSI is a clock signal that sends the clock signals from master to slave.",
            "MOSI is a data line that sends the data from master to slave.",
            "None of the these"
        ],
        "answer": "MOSI is a data line that sends the data from master to slave.",
        "explanation": "Description: MOSI stands for Master Out Slave In. MOSI is a data line that sends the data from master to slave.",
        "codeblock": null
    },
    {
        "question": "30) What is the full form of HART?",
        "options": [
            "Highway Application Remote Transport",
            "Highway Addressable Remote Transducer",
            "High Address Reduce Transport",
            "High Application Remote Transport"
        ],
        "answer": "Highway Addressable Remote Transducer",
        "explanation": "Description: The full form of HART is Highway Addressable Remote Transducer. It is a master and slave protocol in which a slave device only speaks when spoken by a master.",
        "codeblock": null
    },
    {
        "question": "31) What is the range of z-wave?",
        "options": [
            "30 to 100 m",
            "300 to 1000 m",
            "100 to 1000 m",
            "Only 10 m"
        ],
        "answer": "30 to 100 m",
        "explanation": "Description: The Z-Wave is a low-power Mac protocol designed especially for smart home and small business domains. It covers the range from 30 to 100 m.",
        "codeblock": null
    },
    {
        "question": "32) Which of the following topology is used for ZigBee Smart Energy?",
        "options": [
            "Bus Topology",
            "Ring Topology",
            "Star Topology",
            "Any Topology"
        ],
        "answer": "Star Topology",
        "explanation": "Description: ZigBee Smart Energy is designed for a wide range of IoT applications. It supports a wide range of network topologies, such as star topology.",
        "codeblock": null
    },
    {
        "question": "33) Which of the following protocols does not exist at the data link layer?",
        "options": [
            "ZigBee Smart Energy",
            "LoRaWAN",
            "WirelessHART",
            "Secure MQTT"
        ],
        "answer": "Secure MQTT",
        "explanation": "Description: Secure MQTT is a session layer protocol. It is an extended version of the MQTT protocol that uses encryption based on lightweight attribute-based encryption.",
        "codeblock": null
    },
    {
        "question": "34) Which of the following is the type of SPI controller?",
        "options": [
            "Micro-wire or plus",
            "Microwire",
            "Data SPI",
            "Queued SPI"
        ],
        "answer": "Queued SPI",
        "explanation": "Description: A Queued SPI is a type of SPI controller that is used to send a data queue from the SPI bus.",
        "codeblock": null
    },
    {
        "question": "35) What is MQTT primarily used for?",
        "options": [
            "User communication",
            "System transfer",
            "Machine to Machine Communication",
            "Create connection"
        ],
        "answer": "Machine-to-Machine Communication",
        "explanation": "Description: MQTT is a public messaging protocol. It is designed for lightweight \"Machine to Machine\" communication. It was originally developed by IBM.",
        "codeblock": null
    },
    {
        "question": "36) What is the frequency rate of z-wave?",
        "options": [
            "908.42 GHz",
            "928.49 GHz",
            "888.42 GHz",
            "708.49 GHz"
        ],
        "answer": "908.42 GHz",
        "explanation": "Description: The frequency rate of z-wave is 908.42 GHz. The Z-Wave is a low-power Mac protocol designed especially for smart home and small business domains.",
        "codeblock": null
    },
    {
        "question": "37) What is another name of the tactile sensor?",
        "options": [
            "Weight sensor",
            "Imaging sensor",
            "Proximity sensor",
            "Touch sensor"
        ],
        "answer": "Touch sensor",
        "explanation": "Description: The tactile sensor is also called a touch sensor. It is an electronic sensor used for detecting physical touch. The size of this sensor is very small.",
        "codeblock": null
    },
    {
        "question": "38) How many types of capacitive touch sensors in IoT?",
        "options": [
            "Two types",
            "Five types",
            "Seven types",
            "Nine types"
        ],
        "answer": "Two types",
        "explanation": "Description: Two types of capacitive touch sensors in IoT:",
        "codeblock": null
    },
    {
        "question": "39) Which of the following touch sensors is used in a cell phone?",
        "options": [
            "Resistive touch sensors",
            "Human sensor",
            "Capacitive touch sensor",
            "Follow sensor"
        ],
        "answer": "Capacitive touch sensor",
        "explanation": "Description: The capacitive touch sensors are widely used in portable devices such as cell phones. The main reason for this sensor development on the phone is low cost, durability, and design.",
        "codeblock": null
    },
    {
        "question": "40) Which of the following languages does GSN work on?",
        "options": [
            "Python",
            "JAVA",
            "Android",
            "C++"
        ],
        "answer": "JAVA",
        "explanation": "Description: GSN stands for Global Sensor Network. GSN works on JAVA language because JAVA language is portable in nature. The other language (such as C, C++, Python, and HTML) is not portable in nature.",
        "codeblock": null
    },
    {
        "question": "41) Which of the following is the example of a short-range wireless network?",
        "options": [
            "VPN",
            "Wi-Fi",
            "Internet",
            "WWW"
        ],
        "answer": "Wi-Fi",
        "explanation": "Description: Short-range wireless networks have a very short range. This type of network is used for applications running in the local environment. Examples of this network are Wi-Fi and Bluetooth.",
        "codeblock": null
    }
]